reliq/__init__.py
reliq/libreliq.so
reliq/reliq.py
reliq/wrapper.py
reliq-0.0.46.dist-info/licenses/LICENSE
reliq-0.0.46.dist-info/METADATA
reliq-0.0.46.dist-info/WHEEL
reliq-0.0.46.dist-info/top_level.txt
reliq-0.0.46.dist-info/RECORD
